{
  "run_date": "2026-06-27",
  "generated_at": "2026-06-27T07:52:53Z",
  "stocks_rows": 760,
  "sales_rows": 8814,
  "total_skus": 46,
  "to_ship_count": 26,
  "to_ship_units": 4644,
  "oos_count": 0,
  "overstock_count": 14,
  "unknown_pack": 6,
  "exit_code": 0,
  "clusters": {
    "Центральный": {
      "to_ship": 1368,
      "sku_count": 14,
      "oos": 0,
      "deficit": 5
    },
    "Восточный": {
      "to_ship": 1296,
      "sku_count": 9,
      "oos": 0,
      "deficit": 6
    },
    "Южный": {
      "to_ship": 468,
      "sku_count": 9,
      "oos": 0,
      "deficit": 4
    },
    "Волга": {
      "to_ship": 828,
      "sku_count": 7,
      "oos": 0,
      "deficit": 7
    },
    "Северо-западный": {
      "to_ship": 684,
      "sku_count": 7,
      "oos": 0,
      "deficit": 7
    }
  },
  "skus": [
    {
      "sku": "DE112",
      "cluster": "Центральный",
      "stock": 587,
      "sales_30d": 178,
      "k": 3.3,
      "zone": "OVERSTOCK",
      "to_ship": 0,
      "flag": "",
      "global_oos": false,
      "barcodes": [
        "6913362823450"
      ]
    },
    {
      "sku": "DE116AAAA",
      "cluster": "Центральный",
      "stock": 147,
      "sales_30d": 219,
      "k": 0.67,
      "zone": "DEFICIT",
      "to_ship": 288,
      "flag": "",
      "global_oos": false,
      "barcodes": [
        "6913362824365"
      ]
    },
    {
      "sku": "DE119AA",
      "cluster": "Центральный",
      "stock": 813,
      "sales_30d": 169,
      "k": 4.81,
      "zone": "OVERSTOCK",
      "to_ship": 0,
      "flag": "",
      "global_oos": false,
      "barcodes": [
        "2043323196850"
      ]
    },
    {
      "sku": "DE120AAAA",
      "cluster": "Восточный",
      "stock": 2,
      "sales_30d": 186,
      "k": 0.01,
      "zone": "DEFICIT",
      "to_ship": 288,
      "flag": "⚠️ Возможен дефицит — проверь вручную",
      "global_oos": false,
      "barcodes": [
        "6913362825942"
      ]
    },
    {
      "sku": "DE120AAAA",
      "cluster": "Центральный",
      "stock": 252,
      "sales_30d": 297,
      "k": 0.85,
      "zone": "NORMAL",
      "to_ship": 0,
      "flag": "",
      "global_oos": false,
      "barcodes": [
        "6913362825942"
      ]
    },
    {
      "sku": "DE125",
      "cluster": "Центральный",
      "stock": 522,
      "sales_30d": 164,
      "k": 3.18,
      "zone": "OVERSTOCK",
      "to_ship": 0,
      "flag": "",
      "global_oos": false,
      "barcodes": [
        "6913362829094"
      ]
    },
    {
      "sku": "DE201",
      "cluster": "Восточный",
      "stock": 15,
      "sales_30d": 50,
      "k": 0.3,
      "zone": "DEFICIT",
      "to_ship": 72,
      "flag": "",
      "global_oos": false,
      "barcodes": [
        "4270001210609"
      ]
    },
    {
      "sku": "DE201",
      "cluster": "Центральный",
      "stock": 10,
      "sales_30d": 81,
      "k": 0.12,
      "zone": "DEFICIT",
      "to_ship": 144,
      "flag": "",
      "global_oos": false,
      "barcodes": [
        "4270001210609"
      ]
    },
    {
      "sku": "DE201",
      "cluster": "Южный",
      "stock": 4,
      "sales_30d": 41,
      "k": 0.1,
      "zone": "DEFICIT",
      "to_ship": 72,
      "flag": "⚠️ Возможен дефицит — проверь вручную",
      "global_oos": false,
      "barcodes": [
        "4270001210609"
      ]
    },
    {
      "sku": "DE201AA",
      "cluster": "Волга",
      "stock": 0,
      "sales_30d": 50,
      "k": 0.0,
      "zone": "DEFICIT",
      "to_ship": 108,
      "flag": "🔴 Товар вышел",
      "global_oos": false,
      "barcodes": [
        "OZN1381946886"
      ]
    },
    {
      "sku": "DE201AA",
      "cluster": "Восточный",
      "stock": 2,
      "sales_30d": 67,
      "k": 0.03,
      "zone": "DEFICIT",
      "to_ship": 108,
      "flag": "⚠️ Возможен дефицит — проверь вручную",
      "global_oos": false,
      "barcodes": [
        "OZN1381946886"
      ]
    },
    {
      "sku": "DE201AA",
      "cluster": "Северо-западный",
      "stock": 0,
      "sales_30d": 41,
      "k": 0.0,
      "zone": "DEFICIT",
      "to_ship": 72,
      "flag": "🔴 Товар вышел",
      "global_oos": false,
      "barcodes": [
        "OZN1381946886"
      ]
    },
    {
      "sku": "DE201AA",
      "cluster": "Центральный",
      "stock": 139,
      "sales_30d": 168,
      "k": 0.83,
      "zone": "NORMAL",
      "to_ship": 0,
      "flag": "",
      "global_oos": false,
      "barcodes": [
        "OZN1381946886"
      ]
    },
    {
      "sku": "DE201AA",
      "cluster": "Южный",
      "stock": 557,
      "sales_30d": 74,
      "k": 7.53,
      "zone": "OVERSTOCK",
      "to_ship": 0,
      "flag": "",
      "global_oos": false,
      "barcodes": [
        "OZN1381946886"
      ]
    },
    {
      "sku": "DE202AA",
      "cluster": "Волга",
      "stock": 2,
      "sales_30d": 163,
      "k": 0.01,
      "zone": "DEFICIT",
      "to_ship": 252,
      "flag": "⚠️ Возможен дефицит — проверь вручную",
      "global_oos": false,
      "barcodes": [
        "OZN1359408834"
      ]
    },
    {
      "sku": "DE202AA",
      "cluster": "Восточный",
      "stock": 6,
      "sales_30d": 293,
      "k": 0.02,
      "zone": "DEFICIT",
      "to_ship": 468,
      "flag": "",
      "global_oos": false,
      "barcodes": [
        "OZN1359408834"
      ]
    },
    {
      "sku": "DE202AA",
      "cluster": "Северо-западный",
      "stock": 0,
      "sales_30d": 112,
      "k": 0.0,
      "zone": "DEFICIT",
      "to_ship": 180,
      "flag": "🔴 Товар вышел",
      "global_oos": false,
      "barcodes": [
        "OZN1359408834"
      ]
    },
    {
      "sku": "DE202AA",
      "cluster": "Центральный",
      "stock": 213,
      "sales_30d": 581,
      "k": 0.37,
      "zone": "DEFICIT",
      "to_ship": 684,
      "flag": "",
      "global_oos": false,
      "barcodes": [
        "OZN1359408834"
      ]
    },
    {
      "sku": "DE202AA",
      "cluster": "Южный",
      "stock": 0,
      "sales_30d": 189,
      "k": 0.0,
      "zone": "DEFICIT",
      "to_ship": 288,
      "flag": "🔴 Товар вышел",
      "global_oos": false,
      "barcodes": [
        "OZN1359408834"
      ]
    },
    {
      "sku": "DE203AA",
      "cluster": "Волга",
      "stock": 0,
      "sales_30d": 71,
      "k": 0.0,
      "zone": "DEFICIT",
      "to_ship": 108,
      "flag": "🔴 Товар вышел",
      "global_oos": false,
      "barcodes": [
        "OZN1359365941"
      ]
    },
    {
      "sku": "DE203AA",
      "cluster": "Восточный",
      "stock": 519,
      "sales_30d": 94,
      "k": 5.52,
      "zone": "OVERSTOCK",
      "to_ship": 0,
      "flag": "",
      "global_oos": false,
      "barcodes": [
        "OZN1359365941"
      ]
    },
    {
      "sku": "DE203AA",
      "cluster": "Северо-западный",
      "stock": 0,
      "sales_30d": 55,
      "k": 0.0,
      "zone": "DEFICIT",
      "to_ship": 108,
      "flag": "🔴 Товар вышел",
      "global_oos": false,
      "barcodes": [
        "OZN1359365941"
      ]
    },
    {
      "sku": "DE203AA",
      "cluster": "Центральный",
      "stock": 210,
      "sales_30d": 220,
      "k": 0.95,
      "zone": "NORMAL",
      "to_ship": 0,
      "flag": "",
      "global_oos": false,
      "barcodes": [
        "OZN1359365941"
      ]
    },
    {
      "sku": "DE203AA",
      "cluster": "Южный",
      "stock": 264,
      "sales_30d": 86,
      "k": 3.07,
      "zone": "OVERSTOCK",
      "to_ship": 0,
      "flag": "",
      "global_oos": false,
      "barcodes": [
        "OZN1359365941"
      ]
    },
    {
      "sku": "DE205AA",
      "cluster": "Волга",
      "stock": 0,
      "sales_30d": 40,
      "k": 0.0,
      "zone": "DEFICIT",
      "to_ship": 72,
      "flag": "🔴 Товар вышел",
      "global_oos": false,
      "barcodes": [
        "OZN1359459315"
      ]
    },
    {
      "sku": "DE205AA",
      "cluster": "Восточный",
      "stock": 1,
      "sales_30d": 86,
      "k": 0.01,
      "zone": "DEFICIT",
      "to_ship": 144,
      "flag": "⚠️ Возможен дефицит — проверь вручную",
      "global_oos": false,
      "barcodes": [
        "OZN1359459315"
      ]
    },
    {
      "sku": "DE205AA",
      "cluster": "Северо-западный",
      "stock": 0,
      "sales_30d": 45,
      "k": 0.0,
      "zone": "DEFICIT",
      "to_ship": 72,
      "flag": "🔴 Товар вышел",
      "global_oos": false,
      "barcodes": [
        "OZN1359459315"
      ]
    },
    {
      "sku": "DE205AA",
      "cluster": "Центральный",
      "stock": 70,
      "sales_30d": 153,
      "k": 0.46,
      "zone": "DEFICIT",
      "to_ship": 180,
      "flag": "",
      "global_oos": false,
      "barcodes": [
        "OZN1359459315"
      ]
    },
    {
      "sku": "DE205AA",
      "cluster": "Южный",
      "stock": 0,
      "sales_30d": 71,
      "k": 0.0,
      "zone": "DEFICIT",
      "to_ship": 108,
      "flag": "🔴 Товар вышел",
      "global_oos": false,
      "barcodes": [
        "OZN1359459315"
      ]
    },
    {
      "sku": "DE206AA",
      "cluster": "Волга",
      "stock": 0,
      "sales_30d": 88,
      "k": 0.0,
      "zone": "DEFICIT",
      "to_ship": 144,
      "flag": "🔴 Товар вышел",
      "global_oos": false,
      "barcodes": [
        "2041001965767"
      ]
    },
    {
      "sku": "DE206AA",
      "cluster": "Восточный",
      "stock": 263,
      "sales_30d": 161,
      "k": 1.63,
      "zone": "OVERSTOCK",
      "to_ship": 0,
      "flag": "",
      "global_oos": false,
      "barcodes": [
        "2041001965767"
      ]
    },
    {
      "sku": "DE206AA",
      "cluster": "Северо-западный",
      "stock": 1,
      "sales_30d": 52,
      "k": 0.02,
      "zone": "DEFICIT",
      "to_ship": 108,
      "flag": "⚠️ Возможен дефицит — проверь вручную",
      "global_oos": false,
      "barcodes": [
        "2041001965767"
      ]
    },
    {
      "sku": "DE206AA",
      "cluster": "Центральный",
      "stock": 489,
      "sales_30d": 266,
      "k": 1.84,
      "zone": "OVERSTOCK",
      "to_ship": 0,
      "flag": "",
      "global_oos": false,
      "barcodes": [
        "2041001965767"
      ]
    },
    {
      "sku": "DE206AA",
      "cluster": "Южный",
      "stock": 359,
      "sales_30d": 110,
      "k": 3.26,
      "zone": "OVERSTOCK",
      "to_ship": 0,
      "flag": "",
      "global_oos": false,
      "barcodes": [
        "2041001965767"
      ]
    },
    {
      "sku": "DE207",
      "cluster": "Центральный",
      "stock": 1,
      "sales_30d": 44,
      "k": 0.02,
      "zone": "DEFICIT",
      "to_ship": 72,
      "flag": "⚠️ Возможен дефицит — проверь вручную",
      "global_oos": false,
      "barcodes": [
        "6971663561860"
      ]
    },
    {
      "sku": "DE210",
      "cluster": "Волга",
      "stock": 0,
      "sales_30d": 88,
      "k": 0.0,
      "zone": "DEFICIT",
      "to_ship": 144,
      "flag": "🔴 Товар вышел",
      "global_oos": false,
      "barcodes": [
        "6971663562997"
      ]
    },
    {
      "sku": "DE210",
      "cluster": "Восточный",
      "stock": 3,
      "sales_30d": 129,
      "k": 0.02,
      "zone": "DEFICIT",
      "to_ship": 216,
      "flag": "⚠️ Возможен дефицит — проверь вручную",
      "global_oos": false,
      "barcodes": [
        "6971663562997"
      ]
    },
    {
      "sku": "DE210",
      "cluster": "Северо-западный",
      "stock": 0,
      "sales_30d": 53,
      "k": 0.0,
      "zone": "DEFICIT",
      "to_ship": 144,
      "flag": "🔴 Товар вышел",
      "global_oos": false,
      "barcodes": [
        "6971663562997"
      ]
    },
    {
      "sku": "DE210",
      "cluster": "Центральный",
      "stock": 727,
      "sales_30d": 251,
      "k": 2.9,
      "zone": "OVERSTOCK",
      "to_ship": 0,
      "flag": "",
      "global_oos": false,
      "barcodes": [
        "6971663562997"
      ]
    },
    {
      "sku": "DE210",
      "cluster": "Южный",
      "stock": 395,
      "sales_30d": 90,
      "k": 4.39,
      "zone": "OVERSTOCK",
      "to_ship": 0,
      "flag": "",
      "global_oos": false,
      "barcodes": [
        "6971663562997"
      ]
    },
    {
      "sku": "DE310",
      "cluster": "Волга",
      "stock": 0,
      "sales_30d": 2,
      "k": 0.0,
      "zone": "DEFICIT",
      "to_ship": 0,
      "flag": "🔴 Товар вышел; ⚠️ Unknown pack для SKU DE310",
      "global_oos": false,
      "barcodes": [
        "6971663563000"
      ]
    },
    {
      "sku": "DE310",
      "cluster": "Восточный",
      "stock": 85,
      "sales_30d": 3,
      "k": 28.33,
      "zone": "OVERSTOCK",
      "to_ship": 0,
      "flag": "⚠️ Unknown pack для SKU DE310",
      "global_oos": false,
      "barcodes": [
        "6971663563000"
      ]
    },
    {
      "sku": "DE310",
      "cluster": "Северо-западный",
      "stock": 0,
      "sales_30d": 5,
      "k": 0.0,
      "zone": "DEFICIT",
      "to_ship": 0,
      "flag": "🔴 Товар вышел; ⚠️ Unknown pack для SKU DE310",
      "global_oos": false,
      "barcodes": [
        "6971663563000"
      ]
    },
    {
      "sku": "DE310",
      "cluster": "Центральный",
      "stock": 81,
      "sales_30d": 9,
      "k": 9.0,
      "zone": "OVERSTOCK",
      "to_ship": 0,
      "flag": "⚠️ Unknown pack для SKU DE310",
      "global_oos": false,
      "barcodes": [
        "6971663563000"
      ]
    },
    {
      "sku": "DE310",
      "cluster": "Южный",
      "stock": 210,
      "sales_30d": 3,
      "k": 70.0,
      "zone": "OVERSTOCK",
      "to_ship": 0,
      "flag": "⚠️ Unknown pack для SKU DE310",
      "global_oos": false,
      "barcodes": [
        "6971663563000"
      ]
    },
    {
      "sku": "Напиши описание для Вальбериса.",
      "cluster": "Южный",
      "stock": 0,
      "sales_30d": 1,
      "k": 0.0,
      "zone": "DEFICIT",
      "to_ship": 0,
      "flag": "🔴 Товар вышел; ⚠️ Unknown pack для SKU Напиши описание для Вальбериса.",
      "global_oos": false,
      "barcodes": []
    }
  ]
}