{
  "run_date": "2026-06-15",
  "generated_at": "2026-06-15T11:18:57Z",
  "stocks_rows": 684,
  "sales_rows": 7911,
  "total_skus": 45,
  "to_ship_count": 26,
  "to_ship_units": 4104,
  "oos_count": 0,
  "overstock_count": 16,
  "unknown_pack": 5,
  "exit_code": 0,
  "clusters": {
    "Центральный": {
      "to_ship": 1116,
      "sku_count": 14,
      "oos": 0,
      "deficit": 5
    },
    "Восточный": {
      "to_ship": 1152,
      "sku_count": 9,
      "oos": 0,
      "deficit": 6
    },
    "Волга": {
      "to_ship": 864,
      "sku_count": 8,
      "oos": 0,
      "deficit": 8
    },
    "Южный": {
      "to_ship": 468,
      "sku_count": 8,
      "oos": 0,
      "deficit": 3
    },
    "Северо-западный": {
      "to_ship": 504,
      "sku_count": 6,
      "oos": 0,
      "deficit": 6
    }
  },
  "skus": [
    {
      "sku": "DE112",
      "cluster": "Центральный",
      "stock": 145,
      "sales_30d": 156,
      "k": 0.93,
      "zone": "NORMAL",
      "to_ship": 0,
      "flag": "",
      "global_oos": false,
      "barcodes": [
        "6913362823450"
      ]
    },
    {
      "sku": "DE116AAAA",
      "cluster": "Центральный",
      "stock": 383,
      "sales_30d": 169,
      "k": 2.27,
      "zone": "OVERSTOCK",
      "to_ship": 0,
      "flag": "",
      "global_oos": false,
      "barcodes": [
        "6913362824365"
      ]
    },
    {
      "sku": "DE119AA",
      "cluster": "Центральный",
      "stock": 930,
      "sales_30d": 163,
      "k": 5.71,
      "zone": "OVERSTOCK",
      "to_ship": 0,
      "flag": "",
      "global_oos": false,
      "barcodes": [
        "2043323196850"
      ]
    },
    {
      "sku": "DE120AAAA",
      "cluster": "Восточный",
      "stock": 0,
      "sales_30d": 184,
      "k": 0.0,
      "zone": "DEFICIT",
      "to_ship": 288,
      "flag": "🔴 Товар вышел",
      "global_oos": false,
      "barcodes": [
        "6913362825942"
      ]
    },
    {
      "sku": "DE120AAAA",
      "cluster": "Центральный",
      "stock": 196,
      "sales_30d": 259,
      "k": 0.76,
      "zone": "DEFICIT",
      "to_ship": 288,
      "flag": "",
      "global_oos": false,
      "barcodes": [
        "6913362825942"
      ]
    },
    {
      "sku": "DE201",
      "cluster": "Волга",
      "stock": 2,
      "sales_30d": 61,
      "k": 0.03,
      "zone": "DEFICIT",
      "to_ship": 144,
      "flag": "⚠️ Возможен дефицит — проверь вручную",
      "global_oos": false,
      "barcodes": [
        "4270001210609"
      ]
    },
    {
      "sku": "DE201",
      "cluster": "Восточный",
      "stock": 15,
      "sales_30d": 87,
      "k": 0.17,
      "zone": "DEFICIT",
      "to_ship": 144,
      "flag": "",
      "global_oos": false,
      "barcodes": [
        "4270001210609"
      ]
    },
    {
      "sku": "DE201",
      "cluster": "Центральный",
      "stock": 11,
      "sales_30d": 156,
      "k": 0.07,
      "zone": "DEFICIT",
      "to_ship": 288,
      "flag": "",
      "global_oos": false,
      "barcodes": [
        "4270001210609"
      ]
    },
    {
      "sku": "DE201",
      "cluster": "Южный",
      "stock": 4,
      "sales_30d": 70,
      "k": 0.06,
      "zone": "DEFICIT",
      "to_ship": 144,
      "flag": "⚠️ Возможен дефицит — проверь вручную",
      "global_oos": false,
      "barcodes": [
        "4270001210609"
      ]
    },
    {
      "sku": "DE201AA",
      "cluster": "Волга",
      "stock": 0,
      "sales_30d": 52,
      "k": 0.0,
      "zone": "DEFICIT",
      "to_ship": 108,
      "flag": "🔴 Товар вышел",
      "global_oos": false,
      "barcodes": [
        "OZN1381946886"
      ]
    },
    {
      "sku": "DE201AA",
      "cluster": "Восточный",
      "stock": 15,
      "sales_30d": 62,
      "k": 0.24,
      "zone": "DEFICIT",
      "to_ship": 108,
      "flag": "",
      "global_oos": false,
      "barcodes": [
        "OZN1381946886"
      ]
    },
    {
      "sku": "DE201AA",
      "cluster": "Центральный",
      "stock": 267,
      "sales_30d": 127,
      "k": 2.1,
      "zone": "OVERSTOCK",
      "to_ship": 0,
      "flag": "",
      "global_oos": false,
      "barcodes": [
        "OZN1381946886"
      ]
    },
    {
      "sku": "DE201AA",
      "cluster": "Южный",
      "stock": 594,
      "sales_30d": 74,
      "k": 8.03,
      "zone": "OVERSTOCK",
      "to_ship": 0,
      "flag": "",
      "global_oos": false,
      "barcodes": [
        "OZN1381946886"
      ]
    },
    {
      "sku": "DE202AA",
      "cluster": "Волга",
      "stock": 4,
      "sales_30d": 97,
      "k": 0.04,
      "zone": "DEFICIT",
      "to_ship": 144,
      "flag": "⚠️ Возможен дефицит — проверь вручную",
      "global_oos": false,
      "barcodes": [
        "OZN1359408834"
      ]
    },
    {
      "sku": "DE202AA",
      "cluster": "Восточный",
      "stock": 3,
      "sales_30d": 142,
      "k": 0.02,
      "zone": "DEFICIT",
      "to_ship": 216,
      "flag": "⚠️ Возможен дефицит — проверь вручную",
      "global_oos": false,
      "barcodes": [
        "OZN1359408834"
      ]
    },
    {
      "sku": "DE202AA",
      "cluster": "Северо-западный",
      "stock": 2,
      "sales_30d": 48,
      "k": 0.04,
      "zone": "DEFICIT",
      "to_ship": 72,
      "flag": "⚠️ Возможен дефицит — проверь вручную",
      "global_oos": false,
      "barcodes": [
        "OZN1359408834"
      ]
    },
    {
      "sku": "DE202AA",
      "cluster": "Центральный",
      "stock": 883,
      "sales_30d": 320,
      "k": 2.76,
      "zone": "OVERSTOCK",
      "to_ship": 0,
      "flag": "",
      "global_oos": false,
      "barcodes": [
        "OZN1359408834"
      ]
    },
    {
      "sku": "DE202AA",
      "cluster": "Южный",
      "stock": 0,
      "sales_30d": 98,
      "k": 0.0,
      "zone": "DEFICIT",
      "to_ship": 180,
      "flag": "🔴 Товар вышел",
      "global_oos": false,
      "barcodes": [
        "OZN1359408834"
      ]
    },
    {
      "sku": "DE203AA",
      "cluster": "Волга",
      "stock": 0,
      "sales_30d": 62,
      "k": 0.0,
      "zone": "DEFICIT",
      "to_ship": 108,
      "flag": "🔴 Товар вышел",
      "global_oos": false,
      "barcodes": [
        "OZN1359365941"
      ]
    },
    {
      "sku": "DE203AA",
      "cluster": "Восточный",
      "stock": 567,
      "sales_30d": 98,
      "k": 5.79,
      "zone": "OVERSTOCK",
      "to_ship": 0,
      "flag": "",
      "global_oos": false,
      "barcodes": [
        "OZN1359365941"
      ]
    },
    {
      "sku": "DE203AA",
      "cluster": "Северо-западный",
      "stock": 0,
      "sales_30d": 51,
      "k": 0.0,
      "zone": "DEFICIT",
      "to_ship": 108,
      "flag": "🔴 Товар вышел",
      "global_oos": false,
      "barcodes": [
        "OZN1359365941"
      ]
    },
    {
      "sku": "DE203AA",
      "cluster": "Центральный",
      "stock": 360,
      "sales_30d": 188,
      "k": 1.91,
      "zone": "OVERSTOCK",
      "to_ship": 0,
      "flag": "",
      "global_oos": false,
      "barcodes": [
        "OZN1359365941"
      ]
    },
    {
      "sku": "DE203AA",
      "cluster": "Южный",
      "stock": 287,
      "sales_30d": 102,
      "k": 2.81,
      "zone": "OVERSTOCK",
      "to_ship": 0,
      "flag": "",
      "global_oos": false,
      "barcodes": [
        "OZN1359365941"
      ]
    },
    {
      "sku": "DE205AA",
      "cluster": "Волга",
      "stock": 1,
      "sales_30d": 37,
      "k": 0.03,
      "zone": "DEFICIT",
      "to_ship": 72,
      "flag": "⚠️ Возможен дефицит — проверь вручную",
      "global_oos": false,
      "barcodes": [
        "OZN1359459315"
      ]
    },
    {
      "sku": "DE205AA",
      "cluster": "Восточный",
      "stock": 1,
      "sales_30d": 98,
      "k": 0.01,
      "zone": "DEFICIT",
      "to_ship": 180,
      "flag": "⚠️ Возможен дефицит — проверь вручную",
      "global_oos": false,
      "barcodes": [
        "OZN1359459315"
      ]
    },
    {
      "sku": "DE205AA",
      "cluster": "Северо-западный",
      "stock": 0,
      "sales_30d": 39,
      "k": 0.0,
      "zone": "DEFICIT",
      "to_ship": 72,
      "flag": "🔴 Товар вышел",
      "global_oos": false,
      "barcodes": [
        "OZN1359459315"
      ]
    },
    {
      "sku": "DE205AA",
      "cluster": "Центральный",
      "stock": 213,
      "sales_30d": 135,
      "k": 1.58,
      "zone": "OVERSTOCK",
      "to_ship": 0,
      "flag": "",
      "global_oos": false,
      "barcodes": [
        "OZN1359459315"
      ]
    },
    {
      "sku": "DE205AA",
      "cluster": "Южный",
      "stock": 1,
      "sales_30d": 73,
      "k": 0.01,
      "zone": "DEFICIT",
      "to_ship": 144,
      "flag": "⚠️ Возможен дефицит — проверь вручную",
      "global_oos": false,
      "barcodes": [
        "OZN1359459315"
      ]
    },
    {
      "sku": "DE206",
      "cluster": "Центральный",
      "stock": 1,
      "sales_30d": 42,
      "k": 0.02,
      "zone": "DEFICIT",
      "to_ship": 72,
      "flag": "⚠️ Возможен дефицит — проверь вручную",
      "global_oos": false,
      "barcodes": [
        "4270001210654"
      ]
    },
    {
      "sku": "DE206AA",
      "cluster": "Волга",
      "stock": 0,
      "sales_30d": 90,
      "k": 0.0,
      "zone": "DEFICIT",
      "to_ship": 144,
      "flag": "🔴 Товар вышел",
      "global_oos": false,
      "barcodes": [
        "2041001965767"
      ]
    },
    {
      "sku": "DE206AA",
      "cluster": "Восточный",
      "stock": 328,
      "sales_30d": 174,
      "k": 1.89,
      "zone": "OVERSTOCK",
      "to_ship": 0,
      "flag": "",
      "global_oos": false,
      "barcodes": [
        "2041001965767"
      ]
    },
    {
      "sku": "DE206AA",
      "cluster": "Северо-западный",
      "stock": 1,
      "sales_30d": 51,
      "k": 0.02,
      "zone": "DEFICIT",
      "to_ship": 108,
      "flag": "⚠️ Возможен дефицит — проверь вручную",
      "global_oos": false,
      "barcodes": [
        "2041001965767"
      ]
    },
    {
      "sku": "DE206AA",
      "cluster": "Центральный",
      "stock": 49,
      "sales_30d": 282,
      "k": 0.17,
      "zone": "DEFICIT",
      "to_ship": 396,
      "flag": "",
      "global_oos": false,
      "barcodes": [
        "2041001965767"
      ]
    },
    {
      "sku": "DE206AA",
      "cluster": "Южный",
      "stock": 410,
      "sales_30d": 98,
      "k": 4.18,
      "zone": "OVERSTOCK",
      "to_ship": 0,
      "flag": "",
      "global_oos": false,
      "barcodes": [
        "2041001965767"
      ]
    },
    {
      "sku": "DE207",
      "cluster": "Центральный",
      "stock": 12,
      "sales_30d": 47,
      "k": 0.26,
      "zone": "DEFICIT",
      "to_ship": 72,
      "flag": "",
      "global_oos": false,
      "barcodes": [
        "6971663561860"
      ]
    },
    {
      "sku": "DE210",
      "cluster": "Волга",
      "stock": 0,
      "sales_30d": 87,
      "k": 0.0,
      "zone": "DEFICIT",
      "to_ship": 144,
      "flag": "🔴 Товар вышел",
      "global_oos": false,
      "barcodes": [
        "6971663562997"
      ]
    },
    {
      "sku": "DE210",
      "cluster": "Восточный",
      "stock": 1,
      "sales_30d": 137,
      "k": 0.01,
      "zone": "DEFICIT",
      "to_ship": 216,
      "flag": "⚠️ Возможен дефицит — проверь вручную",
      "global_oos": false,
      "barcodes": [
        "6971663562997"
      ]
    },
    {
      "sku": "DE210",
      "cluster": "Северо-западный",
      "stock": 0,
      "sales_30d": 63,
      "k": 0.0,
      "zone": "DEFICIT",
      "to_ship": 144,
      "flag": "🔴 Товар вышел",
      "global_oos": false,
      "barcodes": [
        "6971663562997"
      ]
    },
    {
      "sku": "DE210",
      "cluster": "Центральный",
      "stock": 928,
      "sales_30d": 223,
      "k": 4.16,
      "zone": "OVERSTOCK",
      "to_ship": 0,
      "flag": "",
      "global_oos": false,
      "barcodes": [
        "6971663562997"
      ]
    },
    {
      "sku": "DE210",
      "cluster": "Южный",
      "stock": 433,
      "sales_30d": 95,
      "k": 4.56,
      "zone": "OVERSTOCK",
      "to_ship": 0,
      "flag": "",
      "global_oos": false,
      "barcodes": [
        "6971663562997"
      ]
    },
    {
      "sku": "DE310",
      "cluster": "Волга",
      "stock": 0,
      "sales_30d": 3,
      "k": 0.0,
      "zone": "DEFICIT",
      "to_ship": 0,
      "flag": "🔴 Товар вышел; ⚠️ Unknown pack для SKU DE310",
      "global_oos": false,
      "barcodes": [
        "6971663563000"
      ]
    },
    {
      "sku": "DE310",
      "cluster": "Восточный",
      "stock": 87,
      "sales_30d": 4,
      "k": 21.75,
      "zone": "OVERSTOCK",
      "to_ship": 0,
      "flag": "⚠️ Unknown pack для SKU DE310",
      "global_oos": false,
      "barcodes": [
        "6971663563000"
      ]
    },
    {
      "sku": "DE310",
      "cluster": "Северо-западный",
      "stock": 0,
      "sales_30d": 3,
      "k": 0.0,
      "zone": "DEFICIT",
      "to_ship": 0,
      "flag": "🔴 Товар вышел; ⚠️ Unknown pack для SKU DE310",
      "global_oos": false,
      "barcodes": [
        "6971663563000"
      ]
    },
    {
      "sku": "DE310",
      "cluster": "Центральный",
      "stock": 87,
      "sales_30d": 7,
      "k": 12.43,
      "zone": "OVERSTOCK",
      "to_ship": 0,
      "flag": "⚠️ Unknown pack для SKU DE310",
      "global_oos": false,
      "barcodes": [
        "6971663563000"
      ]
    },
    {
      "sku": "DE310",
      "cluster": "Южный",
      "stock": 210,
      "sales_30d": 3,
      "k": 70.0,
      "zone": "OVERSTOCK",
      "to_ship": 0,
      "flag": "⚠️ Unknown pack для SKU DE310",
      "global_oos": false,
      "barcodes": [
        "6971663563000"
      ]
    }
  ]
}